opulent_pandas/__init__.py
opulent_pandas/column.py
opulent_pandas/error.py
opulent_pandas/schema.py
opulent_pandas/validator.py
opulent_pandas-0.0.4.dist-info/LICENSE
opulent_pandas-0.0.4.dist-info/METADATA
opulent_pandas-0.0.4.dist-info/WHEEL
opulent_pandas-0.0.4.dist-info/top_level.txt
opulent_pandas-0.0.4.dist-info/RECORD
