Metadata-Version: 2.1
Name: opulent-pandas
Version: 0.0.4
Summary: A package to validate the schema of a pandas dataframe
Home-page: UNKNOWN
Author: Daniel van der Ende
License: UNKNOWN
Platform: UNKNOWN
Requires-Dist: pandas (==0.23.4)
Provides-Extra: lint
Requires-Dist: flake8 (==3.5.0) ; extra == 'lint'
Provides-Extra: test
Requires-Dist: pytest (==4.0.2) ; extra == 'test'
